graphique/__init__.py
graphique/core.py
graphique/inputs.py
graphique/interface.py
graphique/middleware.py
graphique/models.py
graphique/py.typed
graphique/scalars.py
graphique/service.py
graphique/shell.py
graphique-2.0.2.dist-info/licenses/LICENSE.txt
graphique-2.0.2.dist-info/METADATA
graphique-2.0.2.dist-info/WHEEL
graphique-2.0.2.dist-info/top_level.txt
graphique-2.0.2.dist-info/RECORD
