Metadata-Version: 2.4
Name: graphique
Version: 2.0.2
Summary: GraphQL service for python dataframes and parquet datasets.
Author-email: Aric Coady <aric.coady@gmail.com>
License-Expression: Apache-2.0
Project-URL: Homepage, https://github.com/coady/graphique
Project-URL: Documentation, https://coady.github.io/graphique
Project-URL: Changelog, https://github.com/coady/graphique/blob/main/CHANGELOG.md
Project-URL: Issues, https://github.com/coady/graphique/issues
Keywords: graphql,arrow,parquet
Classifier: Development Status :: 5 - Production/Stable
Classifier: Intended Audience :: Developers
Classifier: Intended Audience :: Science/Research
Classifier: Operating System :: OS Independent
Classifier: Programming Language :: Python :: 3
Classifier: Programming Language :: Python :: 3.11
Classifier: Programming Language :: Python :: 3.12
Classifier: Programming Language :: Python :: 3.13
Classifier: Programming Language :: Python :: 3.14
Classifier: Topic :: Database :: Database Engines/Servers
Classifier: Topic :: Internet :: WWW/HTTP :: HTTP Servers
Classifier: Topic :: Internet :: WWW/HTTP :: Indexing/Search
Classifier: Topic :: Software Development :: Libraries :: Python Modules
Classifier: Typing :: Typed
Requires-Python: >=3.11
License-File: LICENSE.txt
Requires-Dist: pyarrow>=20
Requires-Dist: strawberry-graphql[asgi,cli]>=0.288
Requires-Dist: ibis-framework>=10.7
Requires-Dist: pyarrow-hotfix
Requires-Dist: isodate>=0.7
Provides-Extra: server
Requires-Dist: uvicorn[standard]; extra == "server"
Requires-Dist: duckdb; extra == "server"
Provides-Extra: cli
Requires-Dist: tqdm; extra == "cli"
Dynamic: license-file
